ogstools/__init__.py
ogstools/_find_ogs.py
ogstools/_internal.py
ogstools/definitions.py
ogstools/_cli/provide_ogs_cli_tools_via_wheel.py
ogstools/_cli/wrap_cli_tools.py
ogstools/examples/__init__.py
ogstools/examples/analytical_solutions/__init__.py
ogstools/examples/analytical_solutions/_heat_conduction.py
ogstools/examples/analytical_solutions/_steady_state_diffusion.py
ogstools/examples/feflow/CT_2D_line_168.fem
ogstools/examples/feflow/CT_2D_line_28.fem
ogstools/examples/feflow/CT_2D_line_560.fem
ogstools/examples/feflow/HTC.fem
ogstools/examples/feflow/HT_toymodel_Diri.fem
ogstools/examples/feflow/HT_toymodel_Diri_hetero.fem
ogstools/examples/feflow/box_3D_cauchy_areal.fem
ogstools/examples/feflow/box_3D_cauchy_areal_IO_FLOW.fem
ogstools/examples/feflow/box_3D_neumann.fem
ogstools/examples/feflow/box_3D_wellBC.fem
ogstools/examples/gmsh/__init__.py
ogstools/examples/gmsh/cube_mixed.py
ogstools/examples/gmsh/line.py
ogstools/examples/gmsh/quarter_rectangle_with_hole.py
ogstools/examples/logs/ConstViscosityThermalConvection.log
ogstools/examples/logs/parallel_1_info.txt
ogstools/examples/logs/parallel_3_debug.txt
ogstools/examples/logs/petscMPI1.log
ogstools/examples/logs/petscMPI2.log
ogstools/examples/logs/serial_adaptive_timestepping.log
ogstools/examples/logs/serial_convergence_long.txt
ogstools/examples/logs/serial_convergence_short.txt
ogstools/examples/logs/serial_critical.txt
ogstools/examples/logs/serial_info.txt
ogstools/examples/logs/serial_time_step_rejected.txt
ogstools/examples/logs/serial_v2_coupled_ht.txt
ogstools/examples/logs/serial_v2_staggered_ht.txt
ogstools/examples/logs/serial_warning_only.txt
ogstools/examples/logs/staggered_heat_transport_in_stationary_flow.log
ogstools/examples/logs/steady_state_diffusion_parallel.log
ogstools/examples/materiallib/bentonite.yml
ogstools/examples/materiallib/carbon_dioxide.yml
ogstools/examples/materiallib/concrete.yml
ogstools/examples/materiallib/diffusion_coefficients.yml
ogstools-0.7.1.dist-info/licenses/LICENSE
ogstools-0.7.1.dist-info/METADATA
ogstools-0.7.1.dist-info/WHEEL
ogstools-0.7.1.dist-info/entry_points.txt
ogstools-0.7.1.dist-info/top_level.txt
ogstools-0.7.1.dist-info/RECORD
